turbo2csv/__init__.py
turbo2csv/scraper.py
turbo2csv-1.2.0.dist-info/LICENSE
turbo2csv-1.2.0.dist-info/METADATA
turbo2csv-1.2.0.dist-info/WHEEL
turbo2csv-1.2.0.dist-info/top_level.txt
turbo2csv-1.2.0.dist-info/RECORD
