Metadata-Version: 2.1
Name: turbo2csv
Version: 1.2.0
Summary: This is a Python web scraper built to extract car information from Turbo.az, one of the most popular car purchase websites in Azerbaijan.
Home-page: https://github.com/zmmmdf/turbo2csv
Author: Ziya Mammadov
Author-email: ziyamm08@gmail.com
License: MIT
Classifier: License :: OSI Approved :: MIT License
Classifier: Programming Language :: Python :: 3
Classifier: Programming Language :: Python :: 3.6
Classifier: Programming Language :: Python :: 3.7
Classifier: Programming Language :: Python :: 3.8
Classifier: Programming Language :: Python :: 3.9
Classifier: Programming Language :: Python :: 3.10
Requires-Python: >=3.6
License-File: LICENSE
Requires-Dist: selenium
